setup.py
vaspplotsuite/__init__.py
vaspplotsuite/app.py
vaspplotsuite.egg-info/PKG-INFO
vaspplotsuite.egg-info/SOURCES.txt
vaspplotsuite.egg-info/dependency_links.txt
vaspplotsuite.egg-info/entry_points.txt
vaspplotsuite.egg-info/requires.txt
vaspplotsuite.egg-info/top_level.txt
vaspplotsuite/bands/__init__.py
vaspplotsuite/bands/qtdesign/__init__.py
vaspplotsuite/bands/vaspbandtools/__init__.py
vaspplotsuite/bands/vaspbandtools/bandstructure.py
vaspplotsuite/bands/vaspbandtools/simplebands.py
vaspplotsuite/dos/__init__.py
vaspplotsuite/dos/qtdesign/__init__.py
vaspplotsuite/dos/vaspdostools/__init__.py
vaspplotsuite/dos/vaspdostools/dostypes.py
vaspplotsuite/mainwindow/__init__.py
vaspplotsuite/mainwindow/app-logo.png
vaspplotsuite/mainwindow/controller.py
vaspplotsuite/mainwindow/mainwindow.py
vaspplotsuite/static/Montserrat-Regular.ttf
vaspplotsuite/static/__init__.py