Metadata-Version: 2.1
Name: vaspplotsuite
Version: 1.0.5
Summary: A program for analysis and plotting of electronic from VASP output data
Home-page: https://github.com/adam-bialy/vasp-plot-suite
Author: Adam Grzelak
Author-email: contact@adamgrzelak.com
License: MIT
Keywords: VASP,eDOS,band structure,density of states
Platform: UNKNOWN
Classifier: Development Status :: 3 - Alpha
Classifier: License :: OSI Approved :: MIT License
Classifier: Programming Language :: Python :: 3.9
Classifier: Programming Language :: Python :: 3.10
